feios_utils/__init__.py
feios_utils/funcs.py
feios_utils-0.2.0.post1.dist-info/LICENSE
feios_utils-0.2.0.post1.dist-info/METADATA
feios_utils-0.2.0.post1.dist-info/WHEEL
feios_utils-0.2.0.post1.dist-info/top_level.txt
feios_utils-0.2.0.post1.dist-info/RECORD
