Metadata-Version: 2.1
Name: feios-utils
Version: 0.2.0.post1
Summary: A small util package for feios
Home-page: https://github.com/devoter-fyc/fei-ros
Author: fyc
Author-email: fycsfls_winter@126.com
Project-URL: Bug Tracker, https://github.com/devoter-fyc/fei-ros/issues
Classifier: Programming Language :: Python :: 3
Classifier: License :: OSI Approved :: GNU General Public License v3 or later (GPLv3+)
Classifier: Operating System :: OS Independent
Classifier: Development Status :: 5 - Production/Stable
Requires-Python: >=3.5
License-File: LICENSE
